qdcrumbs/__init__.py
qdcrumbs/breadcrumb.py
qdcrumbs/qdcrumb.py
qdcrumbs-0.0.2.dist-info/LICENSE
qdcrumbs-0.0.2.dist-info/METADATA
qdcrumbs-0.0.2.dist-info/WHEEL
qdcrumbs-0.0.2.dist-info/top_level.txt
qdcrumbs-0.0.2.dist-info/RECORD
