Metadata-Version: 2.1
Name: qdcrumbs
Version: 0.0.2
Summary: Easy to use breadcrumbs for webpages using Flask.
Home-page: https://github.com/etpcdev/QDcrumbs
Author: etpcdev
Author-email: etpcdev@gmail.com
License: MIT
Platform: any
Classifier: Programming Language :: Python :: 3
Classifier: License :: OSI Approved :: MIT License
Classifier: Operating System :: OS Independent
Requires-Python: >=3.8
License-File: LICENSE
Requires-Dist: Flask >=3.0.0
